rps/__init__.py
rps/game.py
rps/player.py
rps/utils.py
rock_paper_scissors_py-0.1.4.dist-info/METADATA
rock_paper_scissors_py-0.1.4.dist-info/WHEEL
rock_paper_scissors_py-0.1.4.dist-info/top_level.txt
rock_paper_scissors_py-0.1.4.dist-info/RECORD
