Metadata-Version: 2.4
Name: rock-paper-scissors-py
Version: 0.1.4
Summary: Multi-player and multi-action Rock, Paper, Scissors game client
Requires-Python: >=3.12
Requires-Dist: build>=1.2.2.post1
Requires-Dist: pytest>=8.4.1
